{
  "objectInfo" : {
    "id" : "2fwfZxn7qiGcgGEhJwyNar",
    "name" : "Default",
    "type" : "Project",
    "metadata" : {
      "modelVersion" : {
        "major" : 0,
        "minor" : 0
      },
      "repoInfo" : null,
      "contextAttributes" : [ {
        "name" : "IS_DEF_LOC",
        "value" : "true"
      } ],
      "additionalInfo" : {
        "description" : "Auto-generated Default Project",
        "contentType" : null,
        "documentState" : "COMPLETE"
      }
    }
  },
  "dataFileExtension" : "json",
  "updateTime" : "2024-12-19T20:14:52.775Z",
  "objectRefs" : [ ],
  "readableFileExtension" : null,
  "readableFilePresent" : false
}